queue_map_reduce/__init__.py
queue_map_reduce/debug.py
queue_map_reduce/dummy_queue.py
queue_map_reduce/network_file_system.py
queue_map_reduce/pool.py
queue_map_reduce/utils.py
queue_map_reduce/queue/__init__.py
queue_map_reduce/queue/call.py
queue_map_reduce/queue/job_organization.py
queue_map_reduce/queue/worker_node_script.py
queue_map_reduce/tests/resources/dummy_qdel.py
queue_map_reduce/tests/resources/dummy_qstat.py
queue_map_reduce/tests/resources/dummy_qsub.py
queue_map_reduce/tests/resources/dummy_queue_state.json
queue_map_reduce_sebastian_achim_mueller-1.1.1.dist-info/LICENSE.txt
queue_map_reduce_sebastian_achim_mueller-1.1.1.dist-info/METADATA
queue_map_reduce_sebastian_achim_mueller-1.1.1.dist-info/WHEEL
queue_map_reduce_sebastian_achim_mueller-1.1.1.dist-info/top_level.txt
queue_map_reduce_sebastian_achim_mueller-1.1.1.dist-info/RECORD
