Metadata-Version: 2.1
Name: queue-map-reduce-sebastian-achim-mueller
Version: 1.1.1
Summary: Map and reduce for batch-jobs in distributed computing.
Home-page: https://github.com/cherenkov-plenoscope/queue_map_reduce
Author: Sebastian Achim Mueller
Author-email: sebastian-achim.mueller@mpi-hd.mpg.de
Classifier: Programming Language :: Python :: 3
Classifier: License :: OSI Approved :: MIT License
Classifier: Operating System :: Unix
Classifier: Natural Language :: English
Classifier: Topic :: System :: Distributed Computing
Classifier: Topic :: System :: Clustering
Requires-Python: >=3
License-File: LICENSE.txt
Requires-Dist: qstat (>=0.0.5)
